aiccel/__init__.py
aiccel/_deprecated.py
aiccel/agent.py
aiccel/agent_slim.py
aiccel/base_custom_tool.py
aiccel/cli.py
aiccel/constants.py
aiccel/conversation_memory.py
aiccel/embeddings.py
aiccel/encryption.py
aiccel/exceptions.py
aiccel/fast.py
aiccel/health.py
aiccel/interfaces.py
aiccel/jailbreak.py
aiccel/logger.py
aiccel/logging_config.py
aiccel/manager.py
aiccel/observability.py
aiccel/pandora.py
aiccel/pdf_rag_tool.py
aiccel/privacy.py
aiccel/providers.py
aiccel/providers_base.py
aiccel/request_context.py
aiccel/rerank.py
aiccel/tracing.py
aiccel/agent_core/__init__.py
aiccel/agent_core/orchestrator.py
aiccel/agent_core/prompt_builder.py
aiccel/agent_core/tool_executor.py
aiccel/autonomous/__init__.py
aiccel/autonomous/goal_agent.py
aiccel/autonomous/planner.py
aiccel/autonomous/self_reflection.py
aiccel/core/__init__.py
aiccel/core/config.py
aiccel/core/interfaces.py
aiccel/core/plugin.py
aiccel/core/protocols.py
aiccel/core/response.py
aiccel/core/schemas.py
aiccel/di/__init__.py
aiccel/di/container.py
aiccel/epp/tst.py
aiccel/errors/__init__.py
aiccel/execution/__init__.py
aiccel/execution/local.py
aiccel/execution/orchestrator.py
aiccel/execution/planner.py
aiccel/execution/prompt_builder.py
aiccel/execution/protocol.py
aiccel/execution/runner.py
aiccel/execution/service.py
aiccel/execution/subprocess.py
aiccel/execution/tool_executor.py
aiccel/integrations/__init__.py
aiccel/integrations/fastapi_routes.py
aiccel/integrations/langchain.py
aiccel/integrations/openai_functions.py
aiccel/integrations/webhooks.py
aiccel/mcp/__init__.py
aiccel/mcp/adapter.py
aiccel/mcp/client.py
aiccel/mcp/protocol.py
aiccel/mcp/server.py
aiccel/mcp/adapters/__init__.py
aiccel/mcp/transports/__init__.py
aiccel/orchestration/collaborator.py
aiccel/orchestration/router.py
aiccel/pipeline/__init__.py
aiccel/pipeline/middleware.py
aiccel/providers/__init__.py
aiccel/providers/base.py
aiccel/providers/gemini.py
aiccel/providers/groq.py
aiccel/providers/openai.py
aiccel-3.5.0.dist-info/METADATA
aiccel-3.5.0.dist-info/WHEEL
aiccel-3.5.0.dist-info/entry_points.txt
aiccel-3.5.0.dist-info/top_level.txt
aiccel-3.5.0.dist-info/RECORD
