Metadata-Version: 2.4
Name: aiccel
Version: 3.5.0
Summary: AIccel is a versatile Python library for building lightweight AI agents with multiple LLM providers
Author-email: AROMAL TR <aromaltr2000@gmail.com>
License: MIT
Project-URL: Homepage, https://github.com/AromalTR/aiccel
Project-URL: Repository, https://github.com/AromalTR/aiccel.git
Project-URL: Documentation, https://github.com/AromalTR/aiccel#readme
Project-URL: Bug Tracker, https://github.com/AromalTR/aiccel/issues
Keywords: ai,agents,automation,llm,openai,gemini,groq,multi-agent,agentic-ai,tools,rag
Classifier: Development Status :: 4 - Beta
Classifier: Intended Audience :: Developers
Classifier: Topic :: Software Development :: Libraries :: Python Modules
Classifier: Topic :: Scientific/Engineering :: Artificial Intelligence
Classifier: Programming Language :: Python :: 3
Classifier: Programming Language :: Python :: 3.8
Classifier: Programming Language :: Python :: 3.9
Classifier: Programming Language :: Python :: 3.10
Classifier: Programming Language :: Python :: 3.11
Classifier: Programming Language :: Python :: 3.12
Classifier: License :: OSI Approved :: MIT License
Classifier: Operating System :: OS Independent
Requires-Python: >=3.8
Requires-Dist: openai
Requires-Dist: chromadb
Requires-Dist: PyPDF2
Requires-Dist: requests
Requires-Dist: orjson
Requires-Dist: cachetools
Requires-Dist: tenacity
Requires-Dist: aiohttp
Requires-Dist: numpy
Requires-Dist: google-genai
Requires-Dist: textsplitter
Requires-Dist: FlagEmbedding
Requires-Dist: gliner
Requires-Dist: cryptography
Provides-Extra: dev
Requires-Dist: pytest>=7.0.0; extra == "dev"
Requires-Dist: pytest-asyncio>=0.21.0; extra == "dev"
Requires-Dist: pytest-cov>=4.0.0; extra == "dev"
Requires-Dist: black>=23.0.0; extra == "dev"
Requires-Dist: flake8>=6.0.0; extra == "dev"
Requires-Dist: mypy>=1.0.0; extra == "dev"
Requires-Dist: pandas>=2.0.0; extra == "dev"
Provides-Extra: privacy
Requires-Dist: gliner>=0.1.0; extra == "privacy"
Provides-Extra: all
Requires-Dist: gliner>=0.1.0; extra == "all"
Requires-Dist: transformers; extra == "all"
Requires-Dist: torch; extra == "all"
Provides-Extra: safety
Requires-Dist: transformers; extra == "safety"
Requires-Dist: torch; extra == "safety"
Provides-Extra: execution
Requires-Dist: fastapi; extra == "execution"
Requires-Dist: uvicorn; extra == "execution"
